pwndck/__init__.py
pwndck/__main__.py
pwndck/pwndck.py
pwndck-0.2.dist-info/METADATA
pwndck-0.2.dist-info/WHEEL
pwndck-0.2.dist-info/entry_points.txt
pwndck-0.2.dist-info/licenses/LICENSE
pwndck-0.2.dist-info/RECORD
