Metadata-Version: 2.4
Name: pwndck
Version: 0.2
Summary: Check for leaked passwords in HaveIBeenPwned.
License-File: LICENSE
Keywords: passwords,security,breach,haveibeenpwned
Author: David Steele
Author-email: dsteele@gmail.com
Requires-Python: >=3.9
Classifier: Environment :: Console
Classifier: Development Status :: 5 - Production/Stable
Classifier: Intended Audience :: End Users/Desktop
Classifier: License :: OSI Approved :: GNU General Public License v2 or later (GPLv2+)
Classifier: Natural Language :: English
Classifier: Operating System :: POSIX :: Linux
Classifier: Operating System :: MacOS
Classifier: Operating System :: Microsoft :: Windows
Classifier: Programming Language :: Python :: 3 :: Only
Classifier: Topic :: Security
Requires-Dist: argparse-formatter (>=1.4,<2.0)
Requires-Dist: brotli (>=1.1.0)
Requires-Dist: requests (>=2.32.5,<3.0.0)
Project-URL: Changelog, https://github.com/davesteele/pwndck/blob/main/CHANGELOG.md
Project-URL: Homepage, https://github.com/davesteele/pwndck
Project-URL: Issues, https://github.com/davesteele/pwndck/issues
Project-URL: Source, https://github.com/davesteele/pwndck.git
